CONTRIBUTING.md
MANIFEST.in
README.rst
setup.py
docs/HISTORY.txt
docs/LICENSE.GPL
docs/LICENSE.txt
eea/__init__.py
eea.api.controlpanel.egg-info/PKG-INFO
eea.api.controlpanel.egg-info/SOURCES.txt
eea.api.controlpanel.egg-info/dependency_links.txt
eea.api.controlpanel.egg-info/entry_points.txt
eea.api.controlpanel.egg-info/namespace_packages.txt
eea.api.controlpanel.egg-info/not-zip-safe
eea.api.controlpanel.egg-info/requires.txt
eea.api.controlpanel.egg-info/top_level.txt
eea/api/__init__.py
eea/api/controlpanel/README.txt
eea/api/controlpanel/__init__.py
eea/api/controlpanel/configure.zcml
eea/api/controlpanel/interfaces.py
eea/api/controlpanel/profiles.zcml
eea/api/controlpanel/setuphandlers.py
eea/api/controlpanel/version.txt
eea/api/controlpanel/browser/__init__.py
eea/api/controlpanel/browser/configure.zcml
eea/api/controlpanel/events/__init__.py
eea/api/controlpanel/events/configure.zcml
eea/api/controlpanel/events/handlers.py
eea/api/controlpanel/locales/__init__.py
eea/api/controlpanel/locales/eea.pot
eea/api/controlpanel/locales/plone-manual.pot
eea/api/controlpanel/locales/update.sh
eea/api/controlpanel/locales/bg/LC_MESSAGES/eea.po
eea/api/controlpanel/locales/bg/LC_MESSAGES/plone.po
eea/api/controlpanel/locales/cs/LC_MESSAGES/eea.po
eea/api/controlpanel/locales/cs/LC_MESSAGES/plone.po
eea/api/controlpanel/locales/da/LC_MESSAGES/eea.po
eea/api/controlpanel/locales/da/LC_MESSAGES/plone.po
eea/api/controlpanel/locales/de/LC_MESSAGES/eea.po
eea/api/controlpanel/locales/de/LC_MESSAGES/plone.po
eea/api/controlpanel/locales/el/LC_MESSAGES/eea.po
eea/api/controlpanel/locales/el/LC_MESSAGES/plone.po
eea/api/controlpanel/locales/en/LC_MESSAGES/eea.po
eea/api/controlpanel/locales/en/LC_MESSAGES/plone.po
eea/api/controlpanel/locales/es/LC_MESSAGES/eea.po
eea/api/controlpanel/locales/es/LC_MESSAGES/plone.po
eea/api/controlpanel/locales/et/LC_MESSAGES/eea.po
eea/api/controlpanel/locales/et/LC_MESSAGES/plone.po
eea/api/controlpanel/locales/eu/LC_MESSAGES/eea.po
eea/api/controlpanel/locales/eu/LC_MESSAGES/plone.po
eea/api/controlpanel/locales/fi/LC_MESSAGES/eea.po
eea/api/controlpanel/locales/fi/LC_MESSAGES/plone.po
eea/api/controlpanel/locales/fr/LC_MESSAGES/eea.po
eea/api/controlpanel/locales/fr/LC_MESSAGES/plone.po
eea/api/controlpanel/locales/hr/LC_MESSAGES/eea.po
eea/api/controlpanel/locales/hr/LC_MESSAGES/plone.po
